{"components_banner_index.md":"XDXD7MFg","components_avatar_index.md":"1cKKz0dk","components_aspect-ratio_index.md":"_6FkdnCP","components_badge_index.md":"qNQXOV7D","components_breadcrumbs_index.md":"JGmJbBvd","components_caption_index.md":"Bo1vKiE0","components_text_index.md":"jFoLV0J2","components_input-group_index.md":"cDPAFuX1","components_table_index.md":"Y6qNHxQB","components_wizard_index.md":"EQiOBQKD","components_tour_index.md":"-WgklLDp","components_toggle_index.md":"SJgZPk2x","components_truncate_index.md":"Uo5ZUNzr","foundation_colors_index.md":"wDUYukC5","foundation_typography_index.md":"iWsSxqin","components_accordion_index.md":"GpTdDHYq","components_sheet_index.md":"_nnDZMsd","components_pdf-object_index.md":"VYhSRyo9","components_pdf-object_kitchensink.md":"Nc0uFv5c","components_button_index.md":"YQmz4Hbe","components_calendar_index.md":"hrhuqkti","components_collapse_index.md":"AdwcS1lq","components_ringbar_index.md":"G4AjJ163","components_contextual-bar_index.md":"vi1zrPnm","components_radio_index.md":"j8LE0w4Z","components_tooltip_index.md":"CEshnSN5","docs_editor-setup.md":"dnHigexh","components_camera_index.md":"FXbZG_S0","components_progress_index.md":"s2vNvIZ4","components_tabs_index.md":"VlDu1afL","components_chart_index.md":"O1_Wpexw","components_button-group_index.md":"3MFWtdy2","components_carousel_index.md":"Exhc4ZkU","components_input-color_index.md":"IHkzepo3","components_input-pin_index.md":"-bavUdNr","components_checkbox_index.md":"csEgVRTK","components_table-flex_index.md":"4_5stTgS","components_input-file_index.md":"8mBKZfUj","components_card_index.md":"rGDQscha","icons_getting-started.md":"6eM8jh0m","foundation_borders_index.md":"_LCTiqRz","components_spread_index.md":"Z9vGZf-F","components_popover_index.md":"BIkCu6wm","foundation_variables_index.md":"N2dmSDax","components_markdown_index.md":"ELVXeDLS","styleguide_table_index.md":"D8CXM-7s","styleguide_button_index.md":"a-yXwNNO","icons_changelog.md":"cr3WiATM","components_page_page.md":"OjSzxWHw","foundation_shadows_index.md":"eIJ3kxkI","components_pagination_index.md":"7oFvJGQa","components_pdf-helipad_index.md":"6yyUkuyy","components_shimmer_index.md":"Ut8WppYR","styleguide_pagination_index.md":"VbNqRMU6","components_pdf-text_index.md":"U4tE7ohO","styleguide_progress_index.md":"DcYkFQJA","styleguide_banner_index.md":"WWssLVZi","components_pdf-viewer_index.md":"KI71S5o7","components_cropper_index.md":"PBx4txxG","components_datepicker_index.md":"sVpJhifE","components_popup_index.md":"t8THEFUx","components_progress-indicator_index.md":"x9FGaiT1","components_dialog_index.md":"43k6O8yt","components_dot_index.md":"e2BxPQgX","components_dropdown-subitem_index.md":"3qqtRICo","components_dropdown_index.md":"vdysAgt7","components_progressbar_index.md":"XCm3KY_f","components_input-range_index.md":"8WNX0uI_","components_input_index.md":"4Rq_1vfF","components_dropzone_index.md":"aOqK6xn5","components_filterbar_index.md":"nOvZ5NJ8","components_label_index.md":"47mfEKh0","components_form-group_index.md":"ZtUXAli6","components_list-group_index.md":"Nhfwk9GP","components_form-group_kitchensink.md":"lprZNJxk","components_input-password_index.md":"K9nZ9njm","components_heading_index.md":"ytqYjZOJ","components_modal_index.md":"RfHpJ4HR","components_nav_index.md":"nbXURPcl","components_textarea_index.md":"vkcuV3mR","components_navbar_index.md":"Cu2P2MKC","components_notify_index.md":"nzRWm0WY","components_overlay_index.md":"eRd7ObKq","styleguide_badge_index.md":"YSrJOHUD","components_page_index.md":"4zsus4Am","components_sidebar-menu_index.md":"mxs3m2lr","styleguide_button-group_index.md":"J6E6LPrA","index.md":"020wHvrF","styleguide_navigation_index.md":"x9mzJhLb","components_sidebar_index.md":"eDU3Lc1F","components_toast_index.md":"4r1maylr","docs_browser-support.md":"JmyeZi01","components_signature-draw_index.md":"tfjy4cbg","components_signature-text_index.md":"NXZmv540","components_spinner_index.md":"hqO_dlFC","styleguide_toggle_index.md":"oBA1C94m","components_table-static_index.md":"I1IQRxdv","components_select_index.md":"Fz4s0or9","components_subheading_index.md":"PWWhL25h","components_strengthbar_index.md":"3kjvtqEc","styleguide_avatar_index.md":"Y5mPXYyC","styleguide_card_index.md":"VjUok-1M","docs_getting-started.md":"SLc19xpD","styleguide_check-radio_index.md":"aeulmFV8","styleguide_dropdown_index.md":"YZTD5PKq","components_steps_index.md":"KzedVU6a","ecosystem_index.md":"DhDPe-tj","icons_collections.md":"nZI8OT4I"}
