{"components_avatar_index.md":"40c083bd","components_badge_index.md":"0f77ece8","components_banner_index.md":"ce480139","components_button-group_index.md":"d9e05fd2","components_button_index.md":"c972f74b","components_calendar_index.md":"d1d5d73e","components_camera_index.md":"94516dec","components_caption_index.md":"0f1a2c39","components_card_index.md":"67d617b1","components_chart_index.md":"2a1f338f","components_checkbox_index.md":"b2325863","components_collapse_index.md":"ff361dd8","components_contextual-bar_index.md":"2ba8d0c7","components_cropper_index.md":"2f6090e4","components_datepicker_index.md":"8dc03f52","components_dialog_index.md":"6951854d","components_dot_index.md":"05b3c97d","components_dropdown-subitem_index.md":"0a2bda74","components_dropdown_index.md":"f915d114","components_dropzone_index.md":"96252dd8","components_filterbar_index.md":"c081d30b","components_heading_index.md":"620dc700","components_input_index.md":"d97e0795","components_label_index.md":"03b23cc0","components_modal_index.md":"9e90466d","components_nav_index.md":"4eab3d76","components_navbar_index.md":"68b8c5a2","components_overlay_index.md":"85e609f8","components_progress_index.md":"46c8a04c","components_radio_index.md":"cb989402","components_select_index.md":"59651388","components_sidebar-menu_index.md":"600e623a","components_sidebar_index.md":"52c2ca97","components_signature-draw_index.md":"cbe23799","components_signature-text_index.md":"bdec3630","components_spinner_index.md":"e9733cc8","components_spread_index.md":"f07b0910","components_steps_index.md":"df2a37c5","components_subheading_index.md":"f365cae8","components_table_index.md":"3da76d4e","components_tabs_index.md":"003b7354","components_textarea_index.md":"fafc5574","components_toast_index.md":"bce74347","components_toggle_index.md":"812c7253","components_truncate_index.md":"1508ae5c","components_wizard_index.md":"c371bc50","docs_editor-setup.md":"529f6879","docs_getting-started.md":"b6442e38","ecosystem_index.md":"219c097b","foundation_color_index.md":"1778bf5d","index.md":"9c9fb8be","styleguide_badge_index.md":"18b80270","styleguide_banner_index.md":"c26da65d","styleguide_button-group_index.md":"9416b329","styleguide_button_index.md":"f8d27d08","styleguide_card_index.md":"4a6f3349","styleguide_heading_index.md":"091a8782","styleguide_subheading_index.md":"0d27b6d9"}
