{"assets_icon_changelog.md":"BQAMAOYo","assets_icon_collections.md":"CwsgCJoO","assets_icon_getting-started.md":"Bd6Ushgw","assets_ilustration_changelog.md":"B7VYuiBx","assets_ilustration_collections.md":"BxME_xcM","assets_ilustration_getting-started.md":"J6Ii73qW","components_accordion_index.md":"C7ei_lDo","components_aspect-ratio_index.md":"CIqKsoTE","components_avatar_index.md":"DTUxWxe8","components_badge_index.md":"LlTnzrfq","components_banner_index.md":"BlRV5sa7","components_breadcrumbs_index.md":"D5xjlxmN","components_button-group_index.md":"BQq-opj-","components_button_index.md":"DtllwCrd","components_calendar_index.md":"CWC3VTtb","components_camera_index.md":"b8SkVNBV","components_caption_index.md":"CftexaEG","components_card_index.md":"gSUF3Ped","components_carousel_index.md":"CZJCdQQd","components_chart_index.md":"j69ZLxoR","components_checkbox_index.md":"Chuo9ZmO","components_collapse_index.md":"BdMonBof","components_contextual-bar_index.md":"DrhVgx1D","components_contextual-bar_sample.md":"gvTR4fSQ","components_cropper_index.md":"CNt9QgIs","components_datepicker_index.md":"dx_pquXK","components_dialog_index.md":"CE0hZd3v","components_dot_index.md":"BJz7SYLd","components_dropdown-subitem_index.md":"COH3adAR","components_dropdown_index.md":"DzU8jhxi","components_dropzone_index.md":"BllJlQOV","components_filterbar_index.md":"Bgo5ehbQ","components_form-group_index.md":"D2C_7K6m","components_form-group_kitchensink.md":"D2_Ya-i_","components_heading_index.md":"CVFoLovj","components_input-color_index.md":"B0WWyZDs","components_input-file_index.md":"DIR-mfxD","components_input-group_index.md":"DJe-5IPl","components_input-password_index.md":"CO1oqXT0","components_input-pin_index.md":"B7R8XLfd","components_input-range_index.md":"S9nqbrlC","components_input_index.md":"DQvNRfHp","components_label_index.md":"BZFM5Oc6","components_list-group_index.md":"B9jbhsgC","components_markdown_index.md":"DqM8xDtv","components_modal_index.md":"fPxa9zee","components_nav_index.md":"HF7PHhLT","components_navbar_index.md":"DGeqKsGS","components_notify_index.md":"Cq1wbPtn","components_overlay_index.md":"D_nJTjEC","components_page_index.md":"7PK6MwQK","components_page_page.md":"BIC55vsz","components_pagination_index.md":"D01Y8cUW","components_pdf-helipad_index.md":"w20dcODK","components_pdf-object_index.md":"lnEbpFbr","components_pdf-text_index.md":"CHbS0ZrZ","components_pdf-viewer_index.md":"BViwAdiU","components_popover_index.md":"BCJUavyU","components_popup_index.md":"B4rqROVZ","components_progress-indicator_index.md":"BFp1WTPx","components_progress_index.md":"D9T5tojr","components_progressbar_index.md":"B0KCl_b9","components_pspdfkit_debugger.md":"CqwCjo3c","components_pspdfkit_index.md":"-oJta3z3","components_qrcode_index.md":"D14xBCv6","components_radio_index.md":"D71sAU9K","components_ringbar_index.md":"I63RuDJ6","components_select_index.md":"bcwvJd4C","components_sheet_index.md":"GdBkQmrw","components_shimmer_index.md":"DOAqj-Ob","components_sidebar-menu_index.md":"2aAuC0ZG","components_sidebar_index.md":"DR7WSG-6","components_signature-draw_index.md":"0_Y7-3vA","components_signature-text_index.md":"Cbi_F5y3","components_spinner_index.md":"CiNPAvXh","components_spread_index.md":"VX-dMPfc","components_steps_index.md":"C35i4tsk","components_strengthbar_index.md":"BwWhcvCH","components_subheading_index.md":"Cax8amq2","components_table-flex_index.md":"BtqD86ib","components_table-static_index.md":"l4K14Cok","components_table_index.md":"BPNhoj3h","components_tabs_index.md":"DT9BmDLj","components_text_index.md":"DpkDMXqd","components_textarea_index.md":"ClywFAbs","components_time_index.md":"CeIziJDs","components_timepicker_index.md":"CMCCzwpt","components_toast_index.md":"BZL8tCvr","components_toggle_index.md":"XQqBS-L1","components_tooltip_index.md":"BN8Rv6dn","components_tour_index.md":"Ciq9vkVY","components_truncate_index.md":"iLVpQ_PQ","components_wizard_index.md":"CkjOJOHi","docs_browser-support.md":"nn8QOeb-","docs_editor-setup.md":"Cb-I-d2C","docs_getting-started.md":"D15SFToS","ecosystem_index.md":"COtJWFjM","foundation_borders_index.md":"DNT54HHW","foundation_colors_index.md":"2GtbexB-","foundation_shadows_index.md":"ezEXPvEI","foundation_typography_index.md":"B0PehI7k","foundation_variables_index.md":"BBwSQ-VQ","index.md":"C6H6FKbh","styleguide_avatar_index.md":"WB5OOdMg","styleguide_badge_index.md":"CsNeA83Y","styleguide_banner_index.md":"D2FERQun","styleguide_button-group_index.md":"CtxJJujM","styleguide_button_index.md":"C7qtlrV2","styleguide_card_index.md":"euVsB-BC","styleguide_check-radio_index.md":"45JQD5-V","styleguide_dropdown_index.md":"DvcX319Y","styleguide_navigation_index.md":"zvHXJL_u","styleguide_pagination_index.md":"CQSUvwhe","styleguide_progress_index.md":"CKAlyu1t","styleguide_table_index.md":"DnETU92q","styleguide_toggle_index.md":"B6aoNO4Y","tools_pdf-coordinate-finder.md":"FdvNU4sw","tools_pdf-optimizer.md":"U80wCSQL"}
